dtyper/__init__.py
dtyper/py.typed
dtyper-2.5.0.dist-info/LICENSE
dtyper-2.5.0.dist-info/METADATA
dtyper-2.5.0.dist-info/WHEEL
dtyper-2.5.0.dist-info/RECORD
