Metadata-Version: 2.1
Name: dtyper
Version: 2.5.0
Summary: 🗝 Fix and improve `typer` 🗝
Home-page: https://github.com/rec/dtyper
Author: Tom Ritchford
Author-email: tom@swirly.com
Requires-Python: >=3.8
Classifier: Programming Language :: Python :: 3
Classifier: Programming Language :: Python :: 3.8
Classifier: Programming Language :: Python :: 3.9
Classifier: Programming Language :: Python :: 3.10
Classifier: Programming Language :: Python :: 3.11
Classifier: Programming Language :: Python :: 3.12
Requires-Dist: typer
Project-URL: Documentation, https://rec.github.io/dtyper
Project-URL: Repository, https://github.com/rec/dtyper
